{
    "ts": "2024-02-16 21:01:11",
    "psu": "Reguler",
    "mode": "hhcw",
    "chart": {
        "100025": 906,
        "100026": 55,
        "100027": 7,
        "persen": 100.0
    },
    "table": {
        "1101022002001": {
            "psu": "Reguler",
            "100025": 212,
            "100026": 16,
            "100027": 2,
            "persen": 100,
            "status_progress": true
        },
        "1101022002002": {
            "psu": "Reguler",
            "100025": 225,
            "100026": 12,
            "100027": 2,
            "persen": 100,
            "status_progress": true
        },
        "1101022002003": {
            "psu": "Reguler",
            "100025": 229,
            "100026": 10,
            "100027": 1,
            "persen": 100,
            "status_progress": true
        },
        "1101022002004": {
            "psu": "Reguler",
            "100025": 240,
            "100026": 17,
            "100027": 2,
            "persen": 100,
            "status_progress": true
        }
    },
    "progres": {
        "total": 4,
        "progres": 4
    }
}